ola/ArtNetConfigMessages_pb2.py
ola/ClientWrapper.py
ola/DMXConstants.py
ola/DUBDecoder.py
ola/MACAddress.py
ola/OlaClient.py
ola/Ola_pb2.py
ola/PidStore.py
ola/PidStoreLocation.py
ola/Pids_pb2.py
ola/RDMAPI.py
ola/RDMConstants.py
ola/UID.py
ola/UsbProConfigMessages_pb2.py
ola/Version.py
ola/__init__.py
ola/rpc/Rpc_pb2.py
ola/rpc/SimpleRpcController.py
ola/rpc/StreamRpcChannel.py
ola/rpc/__init__.py
ola-0.10.7.dist-info/WHEEL
ola-0.10.7.dist-info/METADATA
ola-0.10.7.dist-info/RECORD
