Metadata-Version: 2.1
Name: ola
Version: 0.10.7
Summary: Python bindings for OLA, available as a package
Author: Justin Cummins
Author-email: justin@samosec.com
Requires-Python: >=3.7,<4.0
Classifier: Programming Language :: Python :: 3
Classifier: Programming Language :: Python :: 3.7
Requires-Dist: protobuf (>=3.1,<4.0)
